Workbook

Sheet Implants
A1: Name | B1: Object ID | C1: Install location | D1: Grade | E1: Cost (¥) | F1: Underground cost (¥) | G1: Armor | H1: Armor applies to | I1: Durability | J1: Power draw (kJ/h) | K1: Quality fee (¥/visit) | L1: Skills / stats modified | M1: Nanohacks permitted | N1: Install requirements | O1: Other benefits / maluses
A2: Neural Link | B2: trl_imp_cortex | C2: Head / cortex | D2: 3 | E2: 4200 | F2: =ROUND(E2*0.8,0) -> 3360 | G2: 1 | H2: head | I2: 30 | J2: =2*2^(MAX(D2-2,0)) -> 4 | K2: =MIN(MAX(D2-1,1),3)*100 -> 200 | L2: +4% to hit; aim speed +0.25 | N2: None (buy, empty slot) | O2: Wireless interface and skull lattice. Live.
A3: Optic Suite | B3: trl_imp_optics | C3: Eyes | D3: 2 | E3: 1800 | F3: =ROUND(E3*0.8,0) -> 1440 | G3: 0 | I3: 20 | J3: =2*2^(MAX(D3-2,0)) -> 2 | K3: =MIN(MAX(D3-1,1),3)*100 -> 100 | L3: +2% to hit; +5% more at 5+ tiles | N3: None (buy, empty slot) | O3: Ranging overlay. Live.
A4: Thermal Vision | B4: trl_imp_thermal | C4: Eyes | D4: 2 | E4: 2600 | F4: =ROUND(E4*0.8,0) -> 2080 | G4: 0 | I4: 20 | J4: =2*2^(MAX(D4-2,0)) -> 2 | K4: =MIN(MAX(D4-1,1),3)*100 -> 100 | L4: +3% to hit | N4: None (buy, empty slot) | O4: Warm bodies show through cover and smoke. Live.
A5: Dorsal Jump Jets | B5: trl_imp_jets | C5: Spine | D5: 2 | E5: 3000 | F5: =ROUND(E5*0.8,0) -> 2400 | G5: 0 | I5: 20 | J5: =2*2^(MAX(D5-2,0)) -> 2 | K5: =MIN(MAX(D5-1,1),3)*100 -> 100 | N5: None (buy, empty slot) | O5: Short flight; no falling damage while fuel lasts. Live.
A6: Reflex Wires | B6: trl_imp_reflex | C6: Spine | D6: 3 | E6: 6200 | F6: =ROUND(E6*0.8,0) -> 4960 | G6: 0 | I6: 20 | J6: =2*2^(MAX(D6-2,0)) -> 4 | K6: =MIN(MAX(D6-1,1),3)*100 -> 200 | L6: Aim +0.5; dodge blades +10%; dodge bullets +14%; attack speed +10 | N6: None (buy, empty slot) | O6: Grade 3+ can dodge bullets. Live.
A7: Synapse Accelerator | B7: trl_imp_synapse | C7: Spine | D7: 4 | E7: 11000 | F7: =ROUND(E7*0.8,0) -> 8800 | G7: 0 | I7: 20 | J7: =2*2^(MAX(D7-2,0)) -> 8 | K7: =MIN(MAX(D7-1,1),3)*100 -> 300 | L7: Aim +0.5; dodge blades +18%; dodge bullets +26%; attack speed +20 | N7: None (buy, empty slot) | O7: Military grade. Live.
A8: Dermal Plating | B8: trl_imp_dermal | C8: Dermal | D8: 2 | E8: 2200 | F8: =ROUND(E8*0.8,0) -> 1760 | G8: 2 | H8: all limbs | I8: 80 | J8: =2*2^(MAX(D8-2,0)) -> 2 | K8: =MIN(MAX(D8-1,1),3)*100 -> 100 | N8: None (buy, empty slot) | O8: Stops working when plating wears through. Live.
A9: Mantis Blades | B9: trl_imp_mantis | C9: Arms | D9: 3 | E9: 3400 | F9: =ROUND(E9*0.8,0) -> 2720 | G9: 1 | H9: arms | I9: 30 | J9: =2*2^(MAX(D9-2,0)) -> 4 | K9: =MIN(MAX(D9-1,1),3)*100 -> 200 | L9: Attack speed +15 | N9: None (buy, empty slot) | O9: Unfold when hands are empty; cannot be knocked away. Live.
A10: Smartlink Palm | B10: trl_imp_smartlink | C10: Hands | D10: 2 | E10: 1500 | F10: =ROUND(E10*0.8,0) -> 1200 | G10: 0 | I10: 20 | J10: =2*2^(MAX(D10-2,0)) -> 2 | K10: =MIN(MAX(D10-1,1),3)*100 -> 100 | L10: +8% to hit with any firearm; aim +0.1 | N10: None (buy, empty slot) | O10: Gun-to-hand link. Live.
A11: Leg Actuators | B11: trl_imp_legs | C11: Legs | D11: 2 | E11: 1600 | F11: =ROUND(E11*0.8,0) -> 1280 | G11: 1 | H11: legs | I11: 40 | J11: =2*2^(MAX(D11-2,0)) -> 2 | K11: =MIN(MAX(D11-1,1),3)*100 -> 100 | N11: None (buy, empty slot) | O11: Long jumps; softer landings. Live.
A12: Cardiac Booster | B12: trl_imp_heart | C12: Chest / organs | D12: 2 | E12: 2800 | F12: =ROUND(E12*0.8,0) -> 2240 | G12: 1 | H12: chest | I12: 30 | J12: =2*2^(MAX(D12-2,0)) -> 2 | K12: =MIN(MAX(D12-1,1),3)*100 -> 100 | N12: None (buy, empty slot) | O12: Planned: bigger stamina reserve. NOT LIVE.
A13: Gecko Grip | B13: trl_imp_grip | C13: Hands | D13: 2 | E13: 1700 | F13: =ROUND(E13*0.8,0) -> 1360 | G13: 0 | I13: 20 | J13: =2*2^(MAX(D13-2,0)) -> 2 | K13: =MIN(MAX(D13-1,1),3)*100 -> 100 | N13: None (buy, empty slot) | O13: Planned: climb sheer walls. NOT LIVE.

Sheet Example Implants
A1: Name | B1: Object ID | C1: Install location | D1: Grade | E1: Cost (¥) | F1: Underground cost (¥) | G1: Armor | H1: Armor applies to | I1: Durability (also health) | J1: Latent draw (kJ/h) | K1: Battery (kJ) | L1: Quality fee / repair at 100% damage (¥) | M1: Recharge cost, one week of this implant (¥) | N1: Full battery recharge cost (¥) | O1: Skills modified | P1: Nanohacks permitted | Q1: Install requirements | R1: Other benefits / maluses
A2: Gutterline Trilobit | B2: trl_imp_x101 | C2: Head / cortex | D2: 1 | E2: 10000 | F2: =ROUND(E2*0.8,0) -> 8000 | G2: 1 | H2: head | I2: 16 | J2: ='Power Model'!$B$3*2^(D2-2) -> 0.5 | L2: =ROUND(E2*'Power Model'!$B$11,0) -> 2500 | M2: =ROUND(J2*'Power Model'!$B$4*('Power Model'!$B$7*'Power Model'!$B$8+'Power Model'!$B$9)+E2*'Power Model'!$B$10/100,0) -> 592 | O2: Networking +1 | P2: 2 | Q2: Networking 2 | R2: Brain implant: holds 2 nanohack slots. Durability gain is minimal. Cheap clinic parts: wear out faster, rattle under load.
A3: Kowloon Surplus Trilobit | B3: trl_imp_x102 | C3: Head / cortex | D3: 1 | E3: 10400 | F3: =ROUND(E3*0.8,0) -> 8320 | G3: 1 | H3: head | I3: 18 | J3: ='Power Model'!$B$3*2^(D3-2) -> 0.5 | L3: =ROUND(E3*'Power Model'!$B$11,0) -> 2600 | M3: =ROUND(J3*'Power Model'!$B$4*('Power Model'!$B$7*'Power Model'!$B$8+'Power Model'!$B$9)+E3*'Power Model'!$B$10/100,0) -> 612 | O3: Analysis +1 | P3: 2 | Q3: Analysis 2 | R3: Brain implant: holds 2 nanohack slots. Durability gain is minimal. Cheap clinic parts: wear out faster, rattle under load.
A4: Rustbelt Cyber Trilobit | B4: trl_imp_x103 | C4: Head / cortex | D4: 1 | E4: 10800 | F4: =ROUND(E4*0.8,0) -> 8640 | G4: 1 | H4: head | I4: 22 | J4: ='Power Model'!$B$3*2^(D4-2) -> 0.5 | L4: =ROUND(E4*'Power Model'!$B$11,0) -> 2700 | M4: =ROUND(J4*'Power Model'!$B$4*('Power Model'!$B$7*'Power Model'!$B$8+'Power Model'!$B$9)+E4*'Power Model'!$B$10/100,0) -> 632 | O4: Implementation +1 | P4: 2 | Q4: Implementation 2 | R4: Brain implant: holds 2 nanohack slots. Durability gain is minimal. Cheap clinic parts: wear out faster, rattle under load.
A5: Backalley Works Trilobit | B5: trl_imp_x104 | C5: Head / cortex | D5: 1 | E5: 11200 | F5: =ROUND(E5*0.8,0) -> 8960 | G5: 1 | H5: head | I5: 24 | J5: ='Power Model'!$B$3*2^(D5-2) -> 0.5 | L5: =ROUND(E5*'Power Model'!$B$11,0) -> 2800 | M5: =ROUND(J5*'Power Model'!$B$4*('Power Model'!$B$7*'Power Model'!$B$8+'Power Model'!$B$9)+E5*'Power Model'!$B$10/100,0) -> 652 | O5: Research +1 | P5: 2 | Q5: Research 2 | R5: Brain implant: holds 2 nanohack slots. Durability gain is minimal. Cheap clinic parts: wear out faster, rattle under load.
A6: Gutterline Optic | B6: trl_imp_x105 | C6: Eyes | D6: 1 | E6: 12900 | F6: =ROUND(E6*0.8,0) -> 10320 | G6: 1 | H6: head | I6: 17 | J6: ='Power Model'!$B$3*2^(D6-2) -> 0.5 | L6: =ROUND(E6*'Power Model'!$B$11,0) -> 3225 | M6: =ROUND(J6*'Power Model'!$B$4*('Power Model'!$B$7*'Power Model'!$B$8+'Power Model'!$B$9)+E6*'Power Model'!$B$10/100,0) -> 737 | O6: Streetwise +1 | Q6: Streetwise 2 | R6: Durability gain is minimal. Cheap clinic parts: wear out faster, rattle under load.
A7: Kowloon Surplus Lens | B7: trl_imp_x106 | C7: Eyes | D7: 1 | E7: 13400 | F7: =ROUND(E7*0.8,0) -> 10720 | G7: 1 | H7: head | I7: 20 | J7: ='Power Model'!$B$3*2^(D7-2) -> 0.5 | L7: =ROUND(E7*'Power Model'!$B$11,0) -> 3350 | M7: =ROUND(J7*'Power Model'!$B$4*('Power Model'!$B$7*'Power Model'!$B$8+'Power Model'!$B$9)+E7*'Power Model'!$B$10/100,0) -> 762 | O7: Analysis +1 | Q7: Analysis 2 | R7: Durability gain is minimal. Cheap clinic parts: wear out faster, rattle under load.
A8: Rustbelt Cyber Scope | B8: trl_imp_x107 | C8: Eyes | D8: 1 | E8: 5800 | F8: =ROUND(E8*0.8,0) -> 4640 | G8: 1 | H8: head | I8: 40 | J8: ='Power Model'!$B$3*2^(D8-2) -> 0.5 | L8: =ROUND(E8*'Power Model'!$B$11,0) -> 1450 | M8: =ROUND(J8*'Power Model'!$B$4*('Power Model'!$B$7*'Power Model'!$B$8+'Power Model'!$B$9)+E8*'Power Model'!$B$10/100,0) -> 382 | Q8: None | R8: Durability gain is minimal. Cheap clinic parts: wear out faster, rattle under load.
A9: Backalley Works Reflex Wiring | B9: trl_imp_x108 | C9: Spine | D9: 1 | E9: 12900 | F9: =ROUND(E9*0.8,0) -> 10320 | G9: 2 | H9: chest | I9: 17 | J9: ='Power Model'!$B$3*2^(D9-2) -> 0.5 | L9: =ROUND(E9*'Power Model'!$B$11,0) -> 3225 | M9: =ROUND(J9*'Power Model'!$B$4*('Power Model'!$B$7*'Power Model'!$B$8+'Power Model'!$B$9)+E9*'Power Model'!$B$10/100,0) -> 737 | O9: Melee +1 | Q9: Melee 2 | R9: Durability gain is minimal. Cheap clinic parts: wear out faster, rattle under load.
A10: Gutterline Balance Rod | B10: trl_imp_x109 | C10: Spine | D10: 1 | E10: 13400 | F10: =ROUND(E10*0.8,0) -> 10720 | G10: 1 | H10: chest | I10: 20 | J10: ='Power Model'!$B$3*2^(D10-2) -> 0.5 | L10: =ROUND(E10*'Power Model'!$B$11,0) -> 3350 | M10: =ROUND(J10*'Power Model'!$B$4*('Power Model'!$B$7*'Power Model'!$B$8+'Power Model'!$B$9)+E10*'Power Model'!$B$10/100,0) -> 762 | O10: Dodge +1 | Q10: Dodge 2 | R10: Durability gain is minimal. Cheap clinic parts: wear out faster, rattle under load.
A11: Kowloon Surplus Nerve Weave | B11: trl_imp_x110 | C11: Spine | D11: 1 | E11: 5800 | F11: =ROUND(E11*0.8,0) -> 4640 | G11: 2 | H11: chest | I11: 40 | J11: ='Power Model'!$B$3*2^(D11-2) -> 0.5 | L11: =ROUND(E11*'Power Model'!$B$11,0) -> 1450 | M11: =ROUND(J11*'Power Model'!$B$4*('Power Model'!$B$7*'Power Model'!$B$8+'Power Model'!$B$9)+E11*'Power Model'!$B$10/100,0) -> 382 | Q11: None | R11: Durability gain is minimal. Cheap clinic parts: wear out faster, rattle under load.
A12: Rustbelt Cyber Lung Pack | B12: trl_imp_x111 | C12: Chest / organs | D12: 1 | E12: 12900 | F12: =ROUND(E12*0.8,0) -> 10320 | G12: 1 | H12: chest | I12: 17 | J12: ='Power Model'!$B$3*2^(D12-2) -> 0.5 | K12: ='Power Model'!$B$4*'Power Model'!$B$5*J12 -> 672 | L12: =ROUND(E12*'Power Model'!$B$11,0) -> 3225 | M12: =ROUND(J12*'Power Model'!$B$4*('Power Model'!$B$7*'Power Model'!$B$8+'Power Model'!$B$9)+E12*'Power Model'!$B$10/100,0) -> 737 | N12: =ROUND(K12*('Power Model'!$B$7*'Power Model'!$B$8+'Power Model'!$B$9),0) -> 739 | O12: Manual +1 | Q12: Manual 2 | R12: Chest battery. Durability gain is minimal. Cheap clinic parts: wear out faster, rattle under load.
A13: Backalley Works Heart Pump | B13: trl_imp_x112 | C13: Chest / organs | D13: 1 | E13: 13400 | F13: =ROUND(E13*0.8,0) -> 10720 | G13: 2 | H13: chest | I13: 20 | J13: ='Power Model'!$B$3*2^(D13-2) -> 0.5 | K13: ='Power Model'!$B$4*'Power Model'!$B$5*J13 -> 672 | L13: =ROUND(E13*'Power Model'!$B$11,0) -> 3350 | M13: =ROUND(J13*'Power Model'!$B$4*('Power Model'!$B$7*'Power Model'!$B$8+'Power Model'!$B$9)+E13*'Power Model'!$B$10/100,0) -> 762 | N13: =ROUND(K13*('Power Model'!$B$7*'Power Model'!$B$8+'Power Model'!$B$9),0) -> 739 | O13: Grit +1 | Q13: Grit 2 | R13: Chest battery. Durability gain is minimal. Cheap clinic parts: wear out faster, rattle under load.
A14: Gutterline Reserve Cell | B14: trl_imp_x113 | C14: Chest / organs | D14: 1 | E14: 20300 | F14: =ROUND(E14*0.8,0) -> 16240 | G14: 1 | H14: chest | I14: 40 | J14: ='Power Model'!$B$3*2^(D14-2) -> 0.5 | K14: ='Power Model'!$B$4*'Power Model'!$B$5*J14*'Power Model'!$B$12 -> 2016 | L14: =ROUND(E14*'Power Model'!$B$11,0) -> 5075 | M14: =ROUND(J14*'Power Model'!$B$4*('Power Model'!$B$7*'Power Model'!$B$8+'Power Model'!$B$9)+E14*'Power Model'!$B$10/100,0) -> 1107 | N14: =ROUND(K14*('Power Model'!$B$7*'Power Model'!$B$8+'Power Model'!$B$9),0) -> 2218 | Q14: None | R14: Reserve battery: stores 3x the standard chest battery, no skill bonus. Durability gain is minimal. Cheap clinic parts: wear out faster, rattle under load.
A15: Kowloon Surplus Dermal Plate | B15: trl_imp_x114 | C15: Dermal | D15: 1 | E15: 5500 | F15: =ROUND(E15*0.8,0) -> 4400 | G15: 2 | H15: all limbs | I15: 36 | J15: ='Power Model'!$B$3*2^(D15-2) -> 0.5 | L15: =ROUND(E15*'Power Model'!$B$11,0) -> 1375 | M15: =ROUND(J15*'Power Model'!$B$4*('Power Model'!$B$7*'Power Model'!$B$8+'Power Model'!$B$9)+E15*'Power Model'!$B$10/100,0) -> 367 | O15: Negotiation -1 | Q15: None | R15: Dermal layer: armor-focused, stiff skin costs Negotiation -1. Durability gain is minimal. Cheap clinic parts: wear out faster, rattle under load.
A16: Rustbelt Cyber Skin Weave | B16: trl_imp_x115 | C16: Dermal | D16: 1 | E16: 5700 | F16: =ROUND(E16*0.8,0) -> 4560 | G16: 2 | H16: all limbs | I16: 39 | J16: ='Power Model'!$B$3*2^(D16-2) -> 0.5 | L16: =ROUND(E16*'Power Model'!$B$11,0) -> 1425 | M16: =ROUND(J16*'Power Model'!$B$4*('Power Model'!$B$7*'Power Model'!$B$8+'Power Model'!$B$9)+E16*'Power Model'!$B$10/100,0) -> 377 | O16: Negotiation -1 | Q16: None | R16: Dermal layer: armor-focused, stiff skin costs Negotiation -1. Durability gain is minimal. Cheap clinic parts: wear out faster, rattle under load.
A17: Backalley Works Forearm Frame | B17: trl_imp_x116 | C17: Arms | D17: 1 | E17: 5400 | F17: =ROUND(E17*0.8,0) -> 4320 | G17: 2 | H17: arms | I17: 34 | J17: ='Power Model'!$B$3*2^(D17-2) -> 0.5 | L17: =ROUND(E17*'Power Model'!$B$11,0) -> 1350 | M17: =ROUND(J17*'Power Model'!$B$4*('Power Model'!$B$7*'Power Model'!$B$8+'Power Model'!$B$9)+E17*'Power Model'!$B$10/100,0) -> 362 | Q17: None | R17: Durability gain is minimal. Cheap clinic parts: wear out faster, rattle under load.
A18: Gutterline Strike Servo | B18: trl_imp_x117 | C18: Arms | D18: 1 | E18: 13400 | F18: =ROUND(E18*0.8,0) -> 10720 | G18: 1 | H18: arms | I18: 20 | J18: ='Power Model'!$B$3*2^(D18-2) -> 0.5 | L18: =ROUND(E18*'Power Model'!$B$11,0) -> 3350 | M18: =ROUND(J18*'Power Model'!$B$4*('Power Model'!$B$7*'Power Model'!$B$8+'Power Model'!$B$9)+E18*'Power Model'!$B$10/100,0) -> 762 | O18: Melee +1 | Q18: Melee 2 | R18: Durability gain is minimal. Cheap clinic parts: wear out faster, rattle under load.
A19: Kowloon Surplus Haul Cabling | B19: trl_imp_x118 | C19: Arms | D19: 1 | E19: 13900 | F19: =ROUND(E19*0.8,0) -> 11120 | G19: 2 | H19: arms | I19: 23 | J19: ='Power Model'!$B$3*2^(D19-2) -> 0.5 | L19: =ROUND(E19*'Power Model'!$B$11,0) -> 3475 | M19: =ROUND(J19*'Power Model'!$B$4*('Power Model'!$B$7*'Power Model'!$B$8+'Power Model'!$B$9)+E19*'Power Model'!$B$10/100,0) -> 787 | O19: Unarmed +1 | Q19: Unarmed 2 | R19: Durability gain is minimal. Cheap clinic parts: wear out faster, rattle under load.
A20: Rustbelt Cyber Smart Palm | B20: trl_imp_x119 | C20: Hands | D20: 1 | E20: 5400 | F20: =ROUND(E20*0.8,0) -> 4320 | G20: 1 | H20: arms | I20: 34 | J20: ='Power Model'!$B$3*2^(D20-2) -> 0.5 | L20: =ROUND(E20*'Power Model'!$B$11,0) -> 1350 | M20: =ROUND(J20*'Power Model'!$B$4*('Power Model'!$B$7*'Power Model'!$B$8+'Power Model'!$B$9)+E20*'Power Model'!$B$10/100,0) -> 362 | Q20: None | R20: Durability gain is minimal. Cheap clinic parts: wear out faster, rattle under load.
A21: Backalley Works Fine-Motor Set | B21: trl_imp_x120 | C21: Hands | D21: 1 | E21: 13400 | F21: =ROUND(E21*0.8,0) -> 10720 | G21: 2 | H21: arms | I21: 20 | J21: ='Power Model'!$B$3*2^(D21-2) -> 0.5 | L21: =ROUND(E21*'Power Model'!$B$11,0) -> 3350 | M21: =ROUND(J21*'Power Model'!$B$4*('Power Model'!$B$7*'Power Model'!$B$8+'Power Model'!$B$9)+E21*'Power Model'!$B$10/100,0) -> 762 | O21: Engineering +1 | Q21: Engineering 2 | R21: Durability gain is minimal. Cheap clinic parts: wear out faster, rattle under load.
A22: Gutterline Tool Fingers | B22: trl_imp_x121 | C22: Hands | D22: 1 | E22: 13900 | F22: =ROUND(E22*0.8,0) -> 11120 | G22: 1 | H22: arms | I22: 23 | J22: ='Power Model'!$B$3*2^(D22-2) -> 0.5 | L22: =ROUND(E22*'Power Model'!$B$11,0) -> 3475 | M22: =ROUND(J22*'Power Model'!$B$4*('Power Model'!$B$7*'Power Model'!$B$8+'Power Model'!$B$9)+E22*'Power Model'!$B$10/100,0) -> 787 | O22: Artisan +1 | Q22: Artisan 2 | R22: Durability gain is minimal. Cheap clinic parts: wear out faster, rattle under load.
A23: Kowloon Surplus Actuator | B23: trl_imp_x122 | C23: Legs | D23: 1 | E23: 5400 | F23: =ROUND(E23*0.8,0) -> 4320 | G23: 2 | H23: legs | I23: 34 | J23: ='Power Model'!$B$3*2^(D23-2) -> 0.5 | L23: =ROUND(E23*'Power Model'!$B$11,0) -> 1350 | M23: =ROUND(J23*'Power Model'!$B$4*('Power Model'!$B$7*'Power Model'!$B$8+'Power Model'!$B$9)+E23*'Power Model'!$B$10/100,0) -> 362 | Q23: None | R23: Durability gain is minimal. Cheap clinic parts: wear out faster, rattle under load.
A24: Rustbelt Cyber Shock Spring | B24: trl_imp_x123 | C24: Legs | D24: 1 | E24: 13400 | F24: =ROUND(E24*0.8,0) -> 10720 | G24: 1 | H24: legs | I24: 20 | J24: ='Power Model'!$B$3*2^(D24-2) -> 0.5 | L24: =ROUND(E24*'Power Model'!$B$11,0) -> 3350 | M24: =ROUND(J24*'Power Model'!$B$4*('Power Model'!$B$7*'Power Model'!$B$8+'Power Model'!$B$9)+E24*'Power Model'!$B$10/100,0) -> 762 | O24: Streetwise +1 | Q24: Streetwise 2 | R24: Durability gain is minimal. Cheap clinic parts: wear out faster, rattle under load.
A25: Backalley Works Sprint Tendons | B25: trl_imp_x124 | C25: Legs | D25: 1 | E25: 13900 | F25: =ROUND(E25*0.8,0) -> 11120 | G25: 2 | H25: legs | I25: 23 | J25: ='Power Model'!$B$3*2^(D25-2) -> 0.5 | L25: =ROUND(E25*'Power Model'!$B$11,0) -> 3475 | M25: =ROUND(J25*'Power Model'!$B$4*('Power Model'!$B$7*'Power Model'!$B$8+'Power Model'!$B$9)+E25*'Power Model'!$B$10/100,0) -> 787 | O25: Manual +1 | Q25: Manual 2 | R25: Durability gain is minimal. Cheap clinic parts: wear out faster, rattle under load.
A26: Halden Medical Trilobit | B26: trl_imp_x201 | C26: Head / cortex | D26: 2 | E26: 24800 | F26: =ROUND(E26*0.8,0) -> 19840 | G26: 2 | H26: head | I26: 26 | J26: ='Power Model'!$B$3*2^(D26-2) -> 1 | L26: =ROUND(E26*'Power Model'!$B$11,0) -> 6200 | M26: =ROUND(J26*'Power Model'!$B$4*('Power Model'!$B$7*'Power Model'!$B$8+'Power Model'!$B$9)+E26*'Power Model'!$B$10/100,0) -> 1425 | O26: Networking +1 | P26: 4 | Q26: Networking 2; Grit 1 | R26: Brain implant: holds 4 nanohack slots. Reliable street-clinic grade.
A27: Sumida-Reyes Trilobit | B27: trl_imp_x202 | C27: Head / cortex | D27: 2 | E27: 25900 | F27: =ROUND(E27*0.8,0) -> 20720 | G27: 2 | H27: head | I27: 28 | J27: ='Power Model'!$B$3*2^(D27-2) -> 1 | L27: =ROUND(E27*'Power Model'!$B$11,0) -> 6475 | M27: =ROUND(J27*'Power Model'!$B$4*('Power Model'!$B$7*'Power Model'!$B$8+'Power Model'!$B$9)+E27*'Power Model'!$B$10/100,0) -> 1480 | O27: Analysis +1 | P27: 4 | Q27: Analysis 2; Grit 1 | R27: Brain implant: holds 4 nanohack slots. Reliable street-clinic grade.
A28: Brightwater Biomed Trilobit | B28: trl_imp_x203 | C28: Head / cortex | D28: 2 | E28: 26900 | F28: =ROUND(E28*0.8,0) -> 21520 | G28: 2 | H28: head | I28: 32 | J28: ='Power Model'!$B$3*2^(D28-2) -> 1 | L28: =ROUND(E28*'Power Model'!$B$11,0) -> 6725 | M28: =ROUND(J28*'Power Model'!$B$4*('Power Model'!$B$7*'Power Model'!$B$8+'Power Model'!$B$9)+E28*'Power Model'!$B$10/100,0) -> 1530 | O28: Implementation +1 | P28: 4 | Q28: Implementation 2; Grit 1 | R28: Brain implant: holds 4 nanohack slots. Reliable street-clinic grade.
A29: Corvane Trilobit | B29: trl_imp_x204 | C29: Head / cortex | D29: 2 | E29: 28000 | F29: =ROUND(E29*0.8,0) -> 22400 | G29: 2 | H29: head | I29: 34 | J29: ='Power Model'!$B$3*2^(D29-2) -> 1 | L29: =ROUND(E29*'Power Model'!$B$11,0) -> 7000 | M29: =ROUND(J29*'Power Model'!$B$4*('Power Model'!$B$7*'Power Model'!$B$8+'Power Model'!$B$9)+E29*'Power Model'!$B$10/100,0) -> 1585 | O29: Research +1 | P29: 4 | Q29: Research 2; Grit 1 | R29: Brain implant: holds 4 nanohack slots. Reliable street-clinic grade.
A30: Halden Medical Optic | B30: trl_imp_x205 | C30: Eyes | D30: 2 | E30: 30000 | F30: =ROUND(E30*0.8,0) -> 24000 | G30: 2 | H30: head | I30: 27 | J30: ='Power Model'!$B$3*2^(D30-2) -> 1 | L30: =ROUND(E30*'Power Model'!$B$11,0) -> 7500 | M30: =ROUND(J30*'Power Model'!$B$4*('Power Model'!$B$7*'Power Model'!$B$8+'Power Model'!$B$9)+E30*'Power Model'!$B$10/100,0) -> 1685 | O30: Streetwise +1 | Q30: Streetwise 2; Grit 1 | R30: Reliable street-clinic grade.
A31: Sumida-Reyes Lens | B31: trl_imp_x206 | C31: Eyes | D31: 2 | E31: 31200 | F31: =ROUND(E31*0.8,0) -> 24960 | G31: 2 | H31: head | I31: 30 | J31: ='Power Model'!$B$3*2^(D31-2) -> 1 | L31: =ROUND(E31*'Power Model'!$B$11,0) -> 7800 | M31: =ROUND(J31*'Power Model'!$B$4*('Power Model'!$B$7*'Power Model'!$B$8+'Power Model'!$B$9)+E31*'Power Model'!$B$10/100,0) -> 1745 | O31: Analysis +1 | Q31: Analysis 2; Grit 1 | R31: Reliable street-clinic grade.
A32: Brightwater Biomed Scope | B32: trl_imp_x207 | C32: Eyes | D32: 2 | E32: 32400 | F32: =ROUND(E32*0.8,0) -> 25920 | G32: 2 | H32: head | I32: 33 | J32: ='Power Model'!$B$3*2^(D32-2) -> 1 | L32: =ROUND(E32*'Power Model'!$B$11,0) -> 8100 | M32: =ROUND(J32*'Power Model'!$B$4*('Power Model'!$B$7*'Power Model'!$B$8+'Power Model'!$B$9)+E32*'Power Model'!$B$10/100,0) -> 1805 | O32: Ranged +1 | Q32: Ranged 2; Grit 1 | R32: Reliable street-clinic grade.
A33: Corvane Reflex Wiring | B33: trl_imp_x208 | C33: Spine | D33: 2 | E33: 30000 | F33: =ROUND(E33*0.8,0) -> 24000 | G33: 3 | H33: chest | I33: 27 | J33: ='Power Model'!$B$3*2^(D33-2) -> 1 | L33: =ROUND(E33*'Power Model'!$B$11,0) -> 7500 | M33: =ROUND(J33*'Power Model'!$B$4*('Power Model'!$B$7*'Power Model'!$B$8+'Power Model'!$B$9)+E33*'Power Model'!$B$10/100,0) -> 1685 | O33: Melee +1 | Q33: Melee 2; Grit 1 | R33: Reliable street-clinic grade.
A34: Halden Medical Balance Rod | B34: trl_imp_x209 | C34: Spine | D34: 2 | E34: 31200 | F34: =ROUND(E34*0.8,0) -> 24960 | G34: 2 | H34: chest | I34: 30 | J34: ='Power Model'!$B$3*2^(D34-2) -> 1 | L34: =ROUND(E34*'Power Model'!$B$11,0) -> 7800 | M34: =ROUND(J34*'Power Model'!$B$4*('Power Model'!$B$7*'Power Model'!$B$8+'Power Model'!$B$9)+E34*'Power Model'!$B$10/100,0) -> 1745 | O34: Dodge +1 | Q34: Dodge 2; Grit 1 | R34: Reliable street-clinic grade.
A35: Sumida-Reyes Nerve Weave | B35: trl_imp_x210 | C35: Spine | D35: 2 | E35: 32400 | F35: =ROUND(E35*0.8,0) -> 25920 | G35: 3 | H35: chest | I35: 33 | J35: ='Power Model'!$B$3*2^(D35-2) -> 1 | L35: =ROUND(E35*'Power Model'!$B$11,0) -> 8100 | M35: =ROUND(J35*'Power Model'!$B$4*('Power Model'!$B$7*'Power Model'!$B$8+'Power Model'!$B$9)+E35*'Power Model'!$B$10/100,0) -> 1805 | O35: Unarmed +1 | Q35: Unarmed 2; Grit 1 | R35: Reliable street-clinic grade.
A36: Brightwater Biomed Lung Pack | B36: trl_imp_x211 | C36: Chest / organs | D36: 2 | E36: 30000 | F36: =ROUND(E36*0.8,0) -> 24000 | G36: 2 | H36: chest | I36: 27 | J36: ='Power Model'!$B$3*2^(D36-2) -> 1 | K36: ='Power Model'!$B$4*'Power Model'!$B$5*J36 -> 1344 | L36: =ROUND(E36*'Power Model'!$B$11,0) -> 7500 | M36: =ROUND(J36*'Power Model'!$B$4*('Power Model'!$B$7*'Power Model'!$B$8+'Power Model'!$B$9)+E36*'Power Model'!$B$10/100,0) -> 1685 | N36: =ROUND(K36*('Power Model'!$B$7*'Power Model'!$B$8+'Power Model'!$B$9),0) -> 1478 | O36: Manual +1 | Q36: Manual 2; Grit 1 | R36: Chest battery. Reliable street-clinic grade.
A37: Corvane Heart Pump | B37: trl_imp_x212 | C37: Chest / organs | D37: 2 | E37: 31200 | F37: =ROUND(E37*0.8,0) -> 24960 | G37: 3 | H37: chest | I37: 30 | J37: ='Power Model'!$B$3*2^(D37-2) -> 1 | K37: ='Power Model'!$B$4*'Power Model'!$B$5*J37 -> 1344 | L37: =ROUND(E37*'Power Model'!$B$11,0) -> 7800 | M37: =ROUND(J37*'Power Model'!$B$4*('Power Model'!$B$7*'Power Model'!$B$8+'Power Model'!$B$9)+E37*'Power Model'!$B$10/100,0) -> 1745 | N37: =ROUND(K37*('Power Model'!$B$7*'Power Model'!$B$8+'Power Model'!$B$9),0) -> 1478 | O37: Grit +1 | Q37: Grit 2 | R37: Chest battery. Reliable street-clinic grade.
A38: Halden Medical Reserve Cell | B38: trl_imp_x213 | C38: Chest / organs | D38: 2 | E38: 46000 | F38: =ROUND(E38*0.8,0) -> 36800 | G38: 2 | H38: chest | I38: 59 | J38: ='Power Model'!$B$3*2^(D38-2) -> 1 | K38: ='Power Model'!$B$4*'Power Model'!$B$5*J38*'Power Model'!$B$12 -> 4032 | L38: =ROUND(E38*'Power Model'!$B$11,0) -> 11500 | M38: =ROUND(J38*'Power Model'!$B$4*('Power Model'!$B$7*'Power Model'!$B$8+'Power Model'!$B$9)+E38*'Power Model'!$B$10/100,0) -> 2485 | N38: =ROUND(K38*('Power Model'!$B$7*'Power Model'!$B$8+'Power Model'!$B$9),0) -> 4435 | Q38: Grit 1 | R38: Reserve battery: stores 3x the standard chest battery, no skill bonus. Reliable street-clinic grade.
A39: Sumida-Reyes Dermal Plate | B39: trl_imp_x214 | C39: Dermal | D39: 2 | E39: 30600 | F39: =ROUND(E39*0.8,0) -> 24480 | G39: 3 | H39: all limbs | I39: 28 | J39: ='Power Model'!$B$3*2^(D39-2) -> 1 | L39: =ROUND(E39*'Power Model'!$B$11,0) -> 7650 | M39: =ROUND(J39*'Power Model'!$B$4*('Power Model'!$B$7*'Power Model'!$B$8+'Power Model'!$B$9)+E39*'Power Model'!$B$10/100,0) -> 1715 | O39: Grit +1; Negotiation -1 | Q39: Grit 2 | R39: Dermal layer: armor-focused, stiff skin costs Negotiation -1. Reliable street-clinic grade.
A40: Brightwater Biomed Skin Weave | B40: trl_imp_x215 | C40: Dermal | D40: 2 | E40: 18200 | F40: =ROUND(E40*0.8,0) -> 14560 | G40: 3 | H40: all limbs | I40: 58 | J40: ='Power Model'!$B$3*2^(D40-2) -> 1 | L40: =ROUND(E40*'Power Model'!$B$11,0) -> 4550 | M40: =ROUND(J40*'Power Model'!$B$4*('Power Model'!$B$7*'Power Model'!$B$8+'Power Model'!$B$9)+E40*'Power Model'!$B$10/100,0) -> 1095 | O40: Negotiation -1 | Q40: Grit 1 | R40: Dermal layer: armor-focused, stiff skin costs Negotiation -1. Reliable street-clinic grade.
A41: Corvane Forearm Frame | B41: trl_imp_x216 | C41: Arms | D41: 2 | E41: 30000 | F41: =ROUND(E41*0.8,0) -> 24000 | G41: 3 | H41: arms | I41: 27 | J41: ='Power Model'!$B$3*2^(D41-2) -> 1 | L41: =ROUND(E41*'Power Model'!$B$11,0) -> 7500 | M41: =ROUND(J41*'Power Model'!$B$4*('Power Model'!$B$7*'Power Model'!$B$8+'Power Model'!$B$9)+E41*'Power Model'!$B$10/100,0) -> 1685 | O41: Unarmed +1 | Q41: Unarmed 2; Grit 1 | R41: Reliable street-clinic grade.
A42: Halden Medical Strike Servo | B42: trl_imp_x217 | C42: Arms | D42: 2 | E42: 31200 | F42: =ROUND(E42*0.8,0) -> 24960 | G42: 2 | H42: arms | I42: 30 | J42: ='Power Model'!$B$3*2^(D42-2) -> 1 | L42: =ROUND(E42*'Power Model'!$B$11,0) -> 7800 | M42: =ROUND(J42*'Power Model'!$B$4*('Power Model'!$B$7*'Power Model'!$B$8+'Power Model'!$B$9)+E42*'Power Model'!$B$10/100,0) -> 1745 | O42: Melee +1 | Q42: Melee 2; Grit 1 | R42: Reliable street-clinic grade.
A43: Sumida-Reyes Haul Cabling | B43: trl_imp_x218 | C43: Arms | D43: 2 | E43: 32400 | F43: =ROUND(E43*0.8,0) -> 25920 | G43: 3 | H43: arms | I43: 33 | J43: ='Power Model'!$B$3*2^(D43-2) -> 1 | L43: =ROUND(E43*'Power Model'!$B$11,0) -> 8100 | M43: =ROUND(J43*'Power Model'!$B$4*('Power Model'!$B$7*'Power Model'!$B$8+'Power Model'!$B$9)+E43*'Power Model'!$B$10/100,0) -> 1805 | O43: Manual +1 | Q43: Manual 2; Grit 1 | R43: Reliable street-clinic grade.
A44: Brightwater Biomed Smart Palm | B44: trl_imp_x219 | C44: Hands | D44: 2 | E44: 30000 | F44: =ROUND(E44*0.8,0) -> 24000 | G44: 2 | H44: arms | I44: 27 | J44: ='Power Model'!$B$3*2^(D44-2) -> 1 | L44: =ROUND(E44*'Power Model'!$B$11,0) -> 7500 | M44: =ROUND(J44*'Power Model'!$B$4*('Power Model'!$B$7*'Power Model'!$B$8+'Power Model'!$B$9)+E44*'Power Model'!$B$10/100,0) -> 1685 | O44: Ranged +1 | Q44: Ranged 2; Grit 1 | R44: Reliable street-clinic grade.
A45: Corvane Fine-Motor Set | B45: trl_imp_x220 | C45: Hands | D45: 2 | E45: 31200 | F45: =ROUND(E45*0.8,0) -> 24960 | G45: 3 | H45: arms | I45: 30 | J45: ='Power Model'!$B$3*2^(D45-2) -> 1 | L45: =ROUND(E45*'Power Model'!$B$11,0) -> 7800 | M45: =ROUND(J45*'Power Model'!$B$4*('Power Model'!$B$7*'Power Model'!$B$8+'Power Model'!$B$9)+E45*'Power Model'!$B$10/100,0) -> 1745 | O45: Engineering +1 | Q45: Engineering 2; Grit 1 | R45: Reliable street-clinic grade.
A46: Halden Medical Tool Fingers | B46: trl_imp_x221 | C46: Hands | D46: 2 | E46: 32400 | F46: =ROUND(E46*0.8,0) -> 25920 | G46: 2 | H46: arms | I46: 33 | J46: ='Power Model'!$B$3*2^(D46-2) -> 1 | L46: =ROUND(E46*'Power Model'!$B$11,0) -> 8100 | M46: =ROUND(J46*'Power Model'!$B$4*('Power Model'!$B$7*'Power Model'!$B$8+'Power Model'!$B$9)+E46*'Power Model'!$B$10/100,0) -> 1805 | O46: Artisan +1 | Q46: Artisan 2; Grit 1 | R46: Reliable street-clinic grade.
A47: Sumida-Reyes Actuator | B47: trl_imp_x222 | C47: Legs | D47: 2 | E47: 30000 | F47: =ROUND(E47*0.8,0) -> 24000 | G47: 3 | H47: legs | I47: 27 | J47: ='Power Model'!$B$3*2^(D47-2) -> 1 | L47: =ROUND(E47*'Power Model'!$B$11,0) -> 7500 | M47: =ROUND(J47*'Power Model'!$B$4*('Power Model'!$B$7*'Power Model'!$B$8+'Power Model'!$B$9)+E47*'Power Model'!$B$10/100,0) -> 1685 | O47: Dodge +1 | Q47: Dodge 2; Grit 1 | R47: Reliable street-clinic grade.
A48: Brightwater Biomed Shock Spring | B48: trl_imp_x223 | C48: Legs | D48: 2 | E48: 31200 | F48: =ROUND(E48*0.8,0) -> 24960 | G48: 2 | H48: legs | I48: 30 | J48: ='Power Model'!$B$3*2^(D48-2) -> 1 | L48: =ROUND(E48*'Power Model'!$B$11,0) -> 7800 | M48: =ROUND(J48*'Power Model'!$B$4*('Power Model'!$B$7*'Power Model'!$B$8+'Power Model'!$B$9)+E48*'Power Model'!$B$10/100,0) -> 1745 | O48: Streetwise +1 | Q48: Streetwise 2; Grit 1 | R48: Reliable street-clinic grade.
A49: Corvane Sprint Tendons | B49: trl_imp_x224 | C49: Legs | D49: 2 | E49: 32400 | F49: =ROUND(E49*0.8,0) -> 25920 | G49: 3 | H49: legs | I49: 33 | J49: ='Power Model'!$B$3*2^(D49-2) -> 1 | L49: =ROUND(E49*'Power Model'!$B$11,0) -> 8100 | M49: =ROUND(J49*'Power Model'!$B$4*('Power Model'!$B$7*'Power Model'!$B$8+'Power Model'!$B$9)+E49*'Power Model'!$B$10/100,0) -> 1805 | O49: Manual +1 | Q49: Manual 2; Grit 1 | R49: Reliable street-clinic grade.
A50: Aegis-Tanaka Trilobit | B50: trl_imp_x301 | C50: Head / cortex | D50: 3 | E50: 55900 | F50: =ROUND(E50*0.8,0) -> 44720 | G50: 2 | H50: head | I50: 40 | J50: ='Power Model'!$B$3*2^(D50-2) -> 2 | L50: =ROUND(E50*'Power Model'!$B$11,0) -> 13975 | M50: =ROUND(J50*'Power Model'!$B$4*('Power Model'!$B$7*'Power Model'!$B$8+'Power Model'!$B$9)+E50*'Power Model'!$B$10/100,0) -> 3165 | O50: Networking +2 | P50: 6 | Q50: Networking 3; Grit 2 | R50: Brain implant: holds 6 nanohack slots. Corporate grade; needs licensed servicing.
A51: Orlov & Voss Trilobit | B51: trl_imp_x302 | C51: Head / cortex | D51: 3 | E51: 58300 | F51: =ROUND(E51*0.8,0) -> 46640 | G51: 2 | H51: head | I51: 44 | J51: ='Power Model'!$B$3*2^(D51-2) -> 2 | L51: =ROUND(E51*'Power Model'!$B$11,0) -> 14575 | M51: =ROUND(J51*'Power Model'!$B$4*('Power Model'!$B$7*'Power Model'!$B$8+'Power Model'!$B$9)+E51*'Power Model'!$B$10/100,0) -> 3285 | O51: Analysis +2 | P51: 6 | Q51: Analysis 3; Grit 2 | R51: Brain implant: holds 6 nanohack slots. Corporate grade; needs licensed servicing.
A52: Meridian Cybernetics Trilobit | B52: trl_imp_x303 | C52: Head / cortex | D52: 3 | E52: 60700 | F52: =ROUND(E52*0.8,0) -> 48560 | G52: 2 | H52: head | I52: 46 | J52: ='Power Model'!$B$3*2^(D52-2) -> 2 | L52: =ROUND(E52*'Power Model'!$B$11,0) -> 15175 | M52: =ROUND(J52*'Power Model'!$B$4*('Power Model'!$B$7*'Power Model'!$B$8+'Power Model'!$B$9)+E52*'Power Model'!$B$10/100,0) -> 3405 | O52: Implementation +2 | P52: 6 | Q52: Implementation 3; Grit 2 | R52: Brain implant: holds 6 nanohack slots. Corporate grade; needs licensed servicing.
A53: Veyra Dynamics Trilobit | B53: trl_imp_x304 | C53: Head / cortex | D53: 3 | E53: 63100 | F53: =ROUND(E53*0.8,0) -> 50480 | G53: 2 | H53: head | I53: 50 | J53: ='Power Model'!$B$3*2^(D53-2) -> 2 | L53: =ROUND(E53*'Power Model'!$B$11,0) -> 15775 | M53: =ROUND(J53*'Power Model'!$B$4*('Power Model'!$B$7*'Power Model'!$B$8+'Power Model'!$B$9)+E53*'Power Model'!$B$10/100,0) -> 3525 | O53: Research +2 | P53: 6 | Q53: Research 3; Grit 2 | R53: Brain implant: holds 6 nanohack slots. Corporate grade; needs licensed servicing.
A54: Aegis-Tanaka Optic | B54: trl_imp_x305 | C54: Eyes | D54: 3 | E54: 62200 | F54: =ROUND(E54*0.8,0) -> 49760 | G54: 2 | H54: head | I54: 42 | J54: ='Power Model'!$B$3*2^(D54-2) -> 2 | L54: =ROUND(E54*'Power Model'!$B$11,0) -> 15550 | M54: =ROUND(J54*'Power Model'!$B$4*('Power Model'!$B$7*'Power Model'!$B$8+'Power Model'!$B$9)+E54*'Power Model'!$B$10/100,0) -> 3480 | O54: Streetwise +1; Research +1 | Q54: Streetwise 2; Research 2; Grit 2 | R54: Corporate grade; needs licensed servicing.
A55: Orlov & Voss Lens | B55: trl_imp_x306 | C55: Eyes | D55: 3 | E55: 64800 | F55: =ROUND(E55*0.8,0) -> 51840 | G55: 2 | H55: head | I55: 45 | J55: ='Power Model'!$B$3*2^(D55-2) -> 2 | L55: =ROUND(E55*'Power Model'!$B$11,0) -> 16200 | M55: =ROUND(J55*'Power Model'!$B$4*('Power Model'!$B$7*'Power Model'!$B$8+'Power Model'!$B$9)+E55*'Power Model'!$B$10/100,0) -> 3610 | O55: Analysis +2 | Q55: Analysis 3; Grit 2 | R55: Corporate grade; needs licensed servicing.
A56: Meridian Cybernetics Scope | B56: trl_imp_x307 | C56: Eyes | D56: 3 | E56: 67400 | F56: =ROUND(E56*0.8,0) -> 53920 | G56: 2 | H56: head | I56: 48 | J56: ='Power Model'!$B$3*2^(D56-2) -> 2 | L56: =ROUND(E56*'Power Model'!$B$11,0) -> 16850 | M56: =ROUND(J56*'Power Model'!$B$4*('Power Model'!$B$7*'Power Model'!$B$8+'Power Model'!$B$9)+E56*'Power Model'!$B$10/100,0) -> 3740 | O56: Ranged +1; Streetwise +1 | Q56: Ranged 2; Streetwise 2; Grit 2 | R56: Corporate grade; needs licensed servicing.
A57: Veyra Dynamics Reflex Wiring | B57: trl_imp_x308 | C57: Spine | D57: 3 | E57: 62200 | F57: =ROUND(E57*0.8,0) -> 49760 | G57: 3 | H57: chest | I57: 42 | J57: ='Power Model'!$B$3*2^(D57-2) -> 2 | L57: =ROUND(E57*'Power Model'!$B$11,0) -> 15550 | M57: =ROUND(J57*'Power Model'!$B$4*('Power Model'!$B$7*'Power Model'!$B$8+'Power Model'!$B$9)+E57*'Power Model'!$B$10/100,0) -> 3480 | O57: Melee +2 | Q57: Melee 3; Grit 2 | R57: Corporate grade; needs licensed servicing.
A58: Aegis-Tanaka Balance Rod | B58: trl_imp_x309 | C58: Spine | D58: 3 | E58: 64800 | F58: =ROUND(E58*0.8,0) -> 51840 | G58: 2 | H58: chest | I58: 45 | J58: ='Power Model'!$B$3*2^(D58-2) -> 2 | L58: =ROUND(E58*'Power Model'!$B$11,0) -> 16200 | M58: =ROUND(J58*'Power Model'!$B$4*('Power Model'!$B$7*'Power Model'!$B$8+'Power Model'!$B$9)+E58*'Power Model'!$B$10/100,0) -> 3610 | O58: Melee +1; Dodge +1 | Q58: Melee 2; Dodge 2; Grit 2 | R58: Corporate grade; needs licensed servicing.
A59: Orlov & Voss Nerve Weave | B59: trl_imp_x310 | C59: Spine | D59: 3 | E59: 67400 | F59: =ROUND(E59*0.8,0) -> 53920 | G59: 3 | H59: chest | I59: 48 | J59: ='Power Model'!$B$3*2^(D59-2) -> 2 | L59: =ROUND(E59*'Power Model'!$B$11,0) -> 16850 | M59: =ROUND(J59*'Power Model'!$B$4*('Power Model'!$B$7*'Power Model'!$B$8+'Power Model'!$B$9)+E59*'Power Model'!$B$10/100,0) -> 3740 | O59: Dodge +2 | Q59: Dodge 3; Grit 2 | R59: Corporate grade; needs licensed servicing.
A60: Meridian Cybernetics Lung Pack | B60: trl_imp_x311 | C60: Chest / organs | D60: 3 | E60: 62200 | F60: =ROUND(E60*0.8,0) -> 49760 | G60: 2 | H60: chest | I60: 42 | J60: ='Power Model'!$B$3*2^(D60-2) -> 2 | K60: ='Power Model'!$B$4*'Power Model'!$B$5*J60 -> 2688 | L60: =ROUND(E60*'Power Model'!$B$11,0) -> 15550 | M60: =ROUND(J60*'Power Model'!$B$4*('Power Model'!$B$7*'Power Model'!$B$8+'Power Model'!$B$9)+E60*'Power Model'!$B$10/100,0) -> 3480 | N60: =ROUND(K60*('Power Model'!$B$7*'Power Model'!$B$8+'Power Model'!$B$9),0) -> 2957 | O60: Manual +1; Negotiation +1 | Q60: Manual 2; Negotiation 2; Grit 2 | R60: Chest battery. Corporate grade; needs licensed servicing.
A61: Veyra Dynamics Heart Pump | B61: trl_imp_x312 | C61: Chest / organs | D61: 3 | E61: 64800 | F61: =ROUND(E61*0.8,0) -> 51840 | G61: 3 | H61: chest | I61: 45 | J61: ='Power Model'!$B$3*2^(D61-2) -> 2 | K61: ='Power Model'!$B$4*'Power Model'!$B$5*J61 -> 2688 | L61: =ROUND(E61*'Power Model'!$B$11,0) -> 16200 | M61: =ROUND(J61*'Power Model'!$B$4*('Power Model'!$B$7*'Power Model'!$B$8+'Power Model'!$B$9)+E61*'Power Model'!$B$10/100,0) -> 3610 | N61: =ROUND(K61*('Power Model'!$B$7*'Power Model'!$B$8+'Power Model'!$B$9),0) -> 2957 | O61: Manual +2 | Q61: Manual 3; Grit 2 | R61: Chest battery. Corporate grade; needs licensed servicing.
A62: Aegis-Tanaka Reserve Cell | B62: trl_imp_x313 | C62: Chest / organs | D62: 3 | E62: 94600 | F62: =ROUND(E62*0.8,0) -> 75680 | G62: 2 | H62: chest | I62: 84 | J62: ='Power Model'!$B$3*2^(D62-2) -> 2 | K62: ='Power Model'!$B$4*'Power Model'!$B$5*J62*'Power Model'!$B$12 -> 8064 | L62: =ROUND(E62*'Power Model'!$B$11,0) -> 23650 | M62: =ROUND(J62*'Power Model'!$B$4*('Power Model'!$B$7*'Power Model'!$B$8+'Power Model'!$B$9)+E62*'Power Model'!$B$10/100,0) -> 5100 | N62: =ROUND(K62*('Power Model'!$B$7*'Power Model'!$B$8+'Power Model'!$B$9),0) -> 8870 | Q62: Grit 2 | R62: Reserve battery: stores 3x the standard chest battery, no skill bonus. Corporate grade; needs licensed servicing.
A63: Orlov & Voss Dermal Plate | B63: trl_imp_x314 | C63: Dermal | D63: 3 | E63: 51500 | F63: =ROUND(E63*0.8,0) -> 41200 | G63: 4 | H63: all limbs | I63: 62 | J63: ='Power Model'!$B$3*2^(D63-2) -> 2 | L63: =ROUND(E63*'Power Model'!$B$11,0) -> 12875 | M63: =ROUND(J63*'Power Model'!$B$4*('Power Model'!$B$7*'Power Model'!$B$8+'Power Model'!$B$9)+E63*'Power Model'!$B$10/100,0) -> 2945 | O63: Grit +1; Negotiation -1 | Q63: Grit 2 | R63: Dermal layer: armor-focused, stiff skin costs Negotiation -1. Corporate grade; needs licensed servicing.
A64: Meridian Cybernetics Skin Weave | B64: trl_imp_x315 | C64: Dermal | D64: 3 | E64: 41000 | F64: =ROUND(E64*0.8,0) -> 32800 | G64: 4 | H64: all limbs | I64: 83 | J64: ='Power Model'!$B$3*2^(D64-2) -> 2 | L64: =ROUND(E64*'Power Model'!$B$11,0) -> 10250 | M64: =ROUND(J64*'Power Model'!$B$4*('Power Model'!$B$7*'Power Model'!$B$8+'Power Model'!$B$9)+E64*'Power Model'!$B$10/100,0) -> 2420 | O64: Negotiation -1 | Q64: Grit 2 | R64: Dermal layer: armor-focused, stiff skin costs Negotiation -1. Corporate grade; needs licensed servicing.
A65: Veyra Dynamics Forearm Frame | B65: trl_imp_x316 | C65: Arms | D65: 3 | E65: 62200 | F65: =ROUND(E65*0.8,0) -> 49760 | G65: 3 | H65: arms | I65: 42 | J65: ='Power Model'!$B$3*2^(D65-2) -> 2 | L65: =ROUND(E65*'Power Model'!$B$11,0) -> 15550 | M65: =ROUND(J65*'Power Model'!$B$4*('Power Model'!$B$7*'Power Model'!$B$8+'Power Model'!$B$9)+E65*'Power Model'!$B$10/100,0) -> 3480 | O65: Unarmed +2 | Q65: Unarmed 3; Grit 2 | R65: Corporate grade; needs licensed servicing.
A66: Aegis-Tanaka Strike Servo | B66: trl_imp_x317 | C66: Arms | D66: 3 | E66: 64800 | F66: =ROUND(E66*0.8,0) -> 51840 | G66: 2 | H66: arms | I66: 45 | J66: ='Power Model'!$B$3*2^(D66-2) -> 2 | L66: =ROUND(E66*'Power Model'!$B$11,0) -> 16200 | M66: =ROUND(J66*'Power Model'!$B$4*('Power Model'!$B$7*'Power Model'!$B$8+'Power Model'!$B$9)+E66*'Power Model'!$B$10/100,0) -> 3610 | O66: Melee +1; Manual +1 | Q66: Melee 2; Manual 2; Grit 2 | R66: Corporate grade; needs licensed servicing.
A67: Orlov & Voss Haul Cabling | B67: trl_imp_x318 | C67: Arms | D67: 3 | E67: 67400 | F67: =ROUND(E67*0.8,0) -> 53920 | G67: 3 | H67: arms | I67: 48 | J67: ='Power Model'!$B$3*2^(D67-2) -> 2 | L67: =ROUND(E67*'Power Model'!$B$11,0) -> 16850 | M67: =ROUND(J67*'Power Model'!$B$4*('Power Model'!$B$7*'Power Model'!$B$8+'Power Model'!$B$9)+E67*'Power Model'!$B$10/100,0) -> 3740 | O67: Manual +2 | Q67: Manual 3; Grit 2 | R67: Corporate grade; needs licensed servicing.
A68: Meridian Cybernetics Smart Palm | B68: trl_imp_x319 | C68: Hands | D68: 3 | E68: 62200 | F68: =ROUND(E68*0.8,0) -> 49760 | G68: 2 | H68: arms | I68: 42 | J68: ='Power Model'!$B$3*2^(D68-2) -> 2 | L68: =ROUND(E68*'Power Model'!$B$11,0) -> 15550 | M68: =ROUND(J68*'Power Model'!$B$4*('Power Model'!$B$7*'Power Model'!$B$8+'Power Model'!$B$9)+E68*'Power Model'!$B$10/100,0) -> 3480 | O68: Ranged +1; Engineering +1 | Q68: Ranged 2; Engineering 2; Grit 2 | R68: Corporate grade; needs licensed servicing.
A69: Veyra Dynamics Fine-Motor Set | B69: trl_imp_x320 | C69: Hands | D69: 3 | E69: 64800 | F69: =ROUND(E69*0.8,0) -> 51840 | G69: 3 | H69: arms | I69: 45 | J69: ='Power Model'!$B$3*2^(D69-2) -> 2 | L69: =ROUND(E69*'Power Model'!$B$11,0) -> 16200 | M69: =ROUND(J69*'Power Model'!$B$4*('Power Model'!$B$7*'Power Model'!$B$8+'Power Model'!$B$9)+E69*'Power Model'!$B$10/100,0) -> 3610 | O69: Engineering +2 | Q69: Engineering 3; Grit 2 | R69: Corporate grade; needs licensed servicing.
A70: Aegis-Tanaka Tool Fingers | B70: trl_imp_x321 | C70: Hands | D70: 3 | E70: 67400 | F70: =ROUND(E70*0.8,0) -> 53920 | G70: 2 | H70: arms | I70: 48 | J70: ='Power Model'!$B$3*2^(D70-2) -> 2 | L70: =ROUND(E70*'Power Model'!$B$11,0) -> 16850 | M70: =ROUND(J70*'Power Model'!$B$4*('Power Model'!$B$7*'Power Model'!$B$8+'Power Model'!$B$9)+E70*'Power Model'!$B$10/100,0) -> 3740 | O70: Artisan +1; Engineering +1 | Q70: Artisan 2; Engineering 2; Grit 2 | R70: Corporate grade; needs licensed servicing.
A71: Orlov & Voss Actuator | B71: trl_imp_x322 | C71: Legs | D71: 3 | E71: 62200 | F71: =ROUND(E71*0.8,0) -> 49760 | G71: 3 | H71: legs | I71: 42 | J71: ='Power Model'!$B$3*2^(D71-2) -> 2 | L71: =ROUND(E71*'Power Model'!$B$11,0) -> 15550 | M71: =ROUND(J71*'Power Model'!$B$4*('Power Model'!$B$7*'Power Model'!$B$8+'Power Model'!$B$9)+E71*'Power Model'!$B$10/100,0) -> 3480 | O71: Dodge +2 | Q71: Dodge 3; Grit 2 | R71: Corporate grade; needs licensed servicing.
A72: Meridian Cybernetics Shock Spring | B72: trl_imp_x323 | C72: Legs | D72: 3 | E72: 64800 | F72: =ROUND(E72*0.8,0) -> 51840 | G72: 2 | H72: legs | I72: 45 | J72: ='Power Model'!$B$3*2^(D72-2) -> 2 | L72: =ROUND(E72*'Power Model'!$B$11,0) -> 16200 | M72: =ROUND(J72*'Power Model'!$B$4*('Power Model'!$B$7*'Power Model'!$B$8+'Power Model'!$B$9)+E72*'Power Model'!$B$10/100,0) -> 3610 | O72: Streetwise +1; Grit +1 | Q72: Streetwise 2; Grit 2 | R72: Corporate grade; needs licensed servicing.
A73: Veyra Dynamics Sprint Tendons | B73: trl_imp_x324 | C73: Legs | D73: 3 | E73: 67400 | F73: =ROUND(E73*0.8,0) -> 53920 | G73: 3 | H73: legs | I73: 48 | J73: ='Power Model'!$B$3*2^(D73-2) -> 2 | L73: =ROUND(E73*'Power Model'!$B$11,0) -> 16850 | M73: =ROUND(J73*'Power Model'!$B$4*('Power Model'!$B$7*'Power Model'!$B$8+'Power Model'!$B$9)+E73*'Power Model'!$B$10/100,0) -> 3740 | O73: Manual +2 | Q73: Manual 3; Grit 2 | R73: Corporate grade; needs licensed servicing.
A74: Kestrel Defense Trilobit | B74: trl_imp_x401 | C74: Head / cortex | D74: 4 | E74: 100100 | F74: =ROUND(E74*0.8,0) -> 80080 | G74: 3 | H74: head | I74: 76 | J74: ='Power Model'!$B$3*2^(D74-2) -> 4 | L74: =ROUND(E74*'Power Model'!$B$11,0) -> 25025 | M74: =ROUND(J74*'Power Model'!$B$4*('Power Model'!$B$7*'Power Model'!$B$8+'Power Model'!$B$9)+E74*'Power Model'!$B$10/100,0) -> 5744 | O74: Networking +2 | P74: 8 | Q74: Networking 3; Grit 3 | R74: Brain implant: holds 8 nanohack slots. Restricted stock; heavy power draw.
A75: Volkov Armaments Trilobit | B75: trl_imp_x402 | C75: Head / cortex | D75: 4 | E75: 104400 | F75: =ROUND(E75*0.8,0) -> 83520 | G75: 3 | H75: head | I75: 79 | J75: ='Power Model'!$B$3*2^(D75-2) -> 4 | L75: =ROUND(E75*'Power Model'!$B$11,0) -> 26100 | M75: =ROUND(J75*'Power Model'!$B$4*('Power Model'!$B$7*'Power Model'!$B$8+'Power Model'!$B$9)+E75*'Power Model'!$B$10/100,0) -> 5959 | O75: Analysis +2 | P75: 8 | Q75: Analysis 3; Grit 3 | R75: Brain implant: holds 8 nanohack slots. Restricted stock; heavy power draw.
A76: Blackmere Ordnance Trilobit | B76: trl_imp_x403 | C76: Head / cortex | D76: 4 | E76: 108600 | F76: =ROUND(E76*0.8,0) -> 86880 | G76: 3 | H76: head | I76: 82 | J76: ='Power Model'!$B$3*2^(D76-2) -> 4 | L76: =ROUND(E76*'Power Model'!$B$11,0) -> 27150 | M76: =ROUND(J76*'Power Model'!$B$4*('Power Model'!$B$7*'Power Model'!$B$8+'Power Model'!$B$9)+E76*'Power Model'!$B$10/100,0) -> 6169 | O76: Implementation +2 | P76: 8 | Q76: Implementation 3; Grit 3 | R76: Brain implant: holds 8 nanohack slots. Restricted stock; heavy power draw.
A77: Ironhold Systems Trilobit | B77: trl_imp_x404 | C77: Head / cortex | D77: 4 | E77: 112900 | F77: =ROUND(E77*0.8,0) -> 90320 | G77: 3 | H77: head | I77: 85 | J77: ='Power Model'!$B$3*2^(D77-2) -> 4 | L77: =ROUND(E77*'Power Model'!$B$11,0) -> 28225 | M77: =ROUND(J77*'Power Model'!$B$4*('Power Model'!$B$7*'Power Model'!$B$8+'Power Model'!$B$9)+E77*'Power Model'!$B$10/100,0) -> 6384 | O77: Research +2 | P77: 8 | Q77: Research 3; Grit 3 | R77: Brain implant: holds 8 nanohack slots. Restricted stock; heavy power draw.
A78: Kestrel Defense Optic | B78: trl_imp_x405 | C78: Eyes | D78: 4 | E78: 108700 | F78: =ROUND(E78*0.8,0) -> 86960 | G78: 3 | H78: head | I78: 62 | J78: ='Power Model'!$B$3*2^(D78-2) -> 4 | L78: =ROUND(E78*'Power Model'!$B$11,0) -> 27175 | M78: =ROUND(J78*'Power Model'!$B$4*('Power Model'!$B$7*'Power Model'!$B$8+'Power Model'!$B$9)+E78*'Power Model'!$B$10/100,0) -> 6174 | O78: Streetwise +3 | Q78: Streetwise 4; Grit 3 | R78: Restricted stock; heavy power draw.
A79: Volkov Armaments Lens | B79: trl_imp_x406 | C79: Eyes | D79: 4 | E79: 113200 | F79: =ROUND(E79*0.8,0) -> 90560 | G79: 3 | H79: head | I79: 65 | J79: ='Power Model'!$B$3*2^(D79-2) -> 4 | L79: =ROUND(E79*'Power Model'!$B$11,0) -> 28300 | M79: =ROUND(J79*'Power Model'!$B$4*('Power Model'!$B$7*'Power Model'!$B$8+'Power Model'!$B$9)+E79*'Power Model'!$B$10/100,0) -> 6399 | O79: Analysis +2; Ranged +1 | Q79: Analysis 3; Ranged 2; Grit 3 | R79: Restricted stock; heavy power draw.
A80: Blackmere Ordnance Scope | B80: trl_imp_x407 | C80: Eyes | D80: 4 | E80: 117700 | F80: =ROUND(E80*0.8,0) -> 94160 | G80: 3 | H80: head | I80: 68 | J80: ='Power Model'!$B$3*2^(D80-2) -> 4 | L80: =ROUND(E80*'Power Model'!$B$11,0) -> 29425 | M80: =ROUND(J80*'Power Model'!$B$4*('Power Model'!$B$7*'Power Model'!$B$8+'Power Model'!$B$9)+E80*'Power Model'!$B$10/100,0) -> 6624 | O80: Ranged +3 | Q80: Ranged 4; Grit 3 | R80: Restricted stock; heavy power draw.
A81: Ironhold Systems Reflex Wiring | B81: trl_imp_x408 | C81: Spine | D81: 4 | E81: 108700 | F81: =ROUND(E81*0.8,0) -> 86960 | G81: 4 | H81: chest | I81: 62 | J81: ='Power Model'!$B$3*2^(D81-2) -> 4 | L81: =ROUND(E81*'Power Model'!$B$11,0) -> 27175 | M81: =ROUND(J81*'Power Model'!$B$4*('Power Model'!$B$7*'Power Model'!$B$8+'Power Model'!$B$9)+E81*'Power Model'!$B$10/100,0) -> 6174 | O81: Melee +2; Unarmed +1 | Q81: Melee 3; Unarmed 2; Grit 3 | R81: Restricted stock; heavy power draw.
A82: Kestrel Defense Balance Rod | B82: trl_imp_x409 | C82: Spine | D82: 4 | E82: 113200 | F82: =ROUND(E82*0.8,0) -> 90560 | G82: 3 | H82: chest | I82: 65 | J82: ='Power Model'!$B$3*2^(D82-2) -> 4 | L82: =ROUND(E82*'Power Model'!$B$11,0) -> 28300 | M82: =ROUND(J82*'Power Model'!$B$4*('Power Model'!$B$7*'Power Model'!$B$8+'Power Model'!$B$9)+E82*'Power Model'!$B$10/100,0) -> 6399 | O82: Melee +3 | Q82: Melee 4; Grit 3 | R82: Restricted stock; heavy power draw.
A83: Volkov Armaments Nerve Weave | B83: trl_imp_x410 | C83: Spine | D83: 4 | E83: 117700 | F83: =ROUND(E83*0.8,0) -> 94160 | G83: 4 | H83: chest | I83: 68 | J83: ='Power Model'!$B$3*2^(D83-2) -> 4 | L83: =ROUND(E83*'Power Model'!$B$11,0) -> 29425 | M83: =ROUND(J83*'Power Model'!$B$4*('Power Model'!$B$7*'Power Model'!$B$8+'Power Model'!$B$9)+E83*'Power Model'!$B$10/100,0) -> 6624 | O83: Dodge +2; Unarmed +1 | Q83: Dodge 3; Unarmed 2; Grit 3 | R83: Restricted stock; heavy power draw.
A84: Blackmere Ordnance Lung Pack | B84: trl_imp_x411 | C84: Chest / organs | D84: 4 | E84: 108700 | F84: =ROUND(E84*0.8,0) -> 86960 | G84: 3 | H84: chest | I84: 62 | J84: ='Power Model'!$B$3*2^(D84-2) -> 4 | K84: ='Power Model'!$B$4*'Power Model'!$B$5*J84 -> 5376 | L84: =ROUND(E84*'Power Model'!$B$11,0) -> 27175 | M84: =ROUND(J84*'Power Model'!$B$4*('Power Model'!$B$7*'Power Model'!$B$8+'Power Model'!$B$9)+E84*'Power Model'!$B$10/100,0) -> 6174 | N84: =ROUND(K84*('Power Model'!$B$7*'Power Model'!$B$8+'Power Model'!$B$9),0) -> 5914 | O84: Manual +3 | Q84: Manual 4; Grit 3 | R84: Chest battery. Restricted stock; heavy power draw.
A85: Ironhold Systems Heart Pump | B85: trl_imp_x412 | C85: Chest / organs | D85: 4 | E85: 113200 | F85: =ROUND(E85*0.8,0) -> 90560 | G85: 4 | H85: chest | I85: 65 | J85: ='Power Model'!$B$3*2^(D85-2) -> 4 | K85: ='Power Model'!$B$4*'Power Model'!$B$5*J85 -> 5376 | L85: =ROUND(E85*'Power Model'!$B$11,0) -> 28300 | M85: =ROUND(J85*'Power Model'!$B$4*('Power Model'!$B$7*'Power Model'!$B$8+'Power Model'!$B$9)+E85*'Power Model'!$B$10/100,0) -> 6399 | N85: =ROUND(K85*('Power Model'!$B$7*'Power Model'!$B$8+'Power Model'!$B$9),0) -> 5914 | O85: Manual +2; Grit +1 | Q85: Manual 3; Grit 3 | R85: Chest battery. Restricted stock; heavy power draw.
A86: Kestrel Defense Reserve Cell | B86: trl_imp_x413 | C86: Chest / organs | D86: 4 | E86: 162200 | F86: =ROUND(E86*0.8,0) -> 129760 | G86: 3 | H86: chest | I86: 116 | J86: ='Power Model'!$B$3*2^(D86-2) -> 4 | K86: ='Power Model'!$B$4*'Power Model'!$B$5*J86*'Power Model'!$B$12 -> 16128 | L86: =ROUND(E86*'Power Model'!$B$11,0) -> 40550 | M86: =ROUND(J86*'Power Model'!$B$4*('Power Model'!$B$7*'Power Model'!$B$8+'Power Model'!$B$9)+E86*'Power Model'!$B$10/100,0) -> 8849 | N86: =ROUND(K86*('Power Model'!$B$7*'Power Model'!$B$8+'Power Model'!$B$9),0) -> 17741 | Q86: Grit 3 | R86: Reserve battery: stores 3x the standard chest battery, no skill bonus. Restricted stock; heavy power draw.
A87: Volkov Armaments Dermal Plate | B87: trl_imp_x414 | C87: Dermal | D87: 4 | E87: 100700 | F87: =ROUND(E87*0.8,0) -> 80560 | G87: 5 | H87: all limbs | I87: 79 | J87: ='Power Model'!$B$3*2^(D87-2) -> 4 | L87: =ROUND(E87*'Power Model'!$B$11,0) -> 25175 | M87: =ROUND(J87*'Power Model'!$B$4*('Power Model'!$B$7*'Power Model'!$B$8+'Power Model'!$B$9)+E87*'Power Model'!$B$10/100,0) -> 5774 | O87: Grit +2; Negotiation -1 | Q87: Grit 3 | R87: Dermal layer: armor-focused, stiff skin costs Negotiation -1. Restricted stock; heavy power draw.
A88: Blackmere Ordnance Skin Weave | B88: trl_imp_x415 | C88: Dermal | D88: 4 | E88: 83400 | F88: =ROUND(E88*0.8,0) -> 66720 | G88: 5 | H88: all limbs | I88: 114 | J88: ='Power Model'!$B$3*2^(D88-2) -> 4 | L88: =ROUND(E88*'Power Model'!$B$11,0) -> 20850 | M88: =ROUND(J88*'Power Model'!$B$4*('Power Model'!$B$7*'Power Model'!$B$8+'Power Model'!$B$9)+E88*'Power Model'!$B$10/100,0) -> 4909 | O88: Negotiation -1 | Q88: Grit 3 | R88: Dermal layer: armor-focused, stiff skin costs Negotiation -1. Restricted stock; heavy power draw.
A89: Ironhold Systems Forearm Frame | B89: trl_imp_x416 | C89: Arms | D89: 4 | E89: 108700 | F89: =ROUND(E89*0.8,0) -> 86960 | G89: 4 | H89: arms | I89: 62 | J89: ='Power Model'!$B$3*2^(D89-2) -> 4 | L89: =ROUND(E89*'Power Model'!$B$11,0) -> 27175 | M89: =ROUND(J89*'Power Model'!$B$4*('Power Model'!$B$7*'Power Model'!$B$8+'Power Model'!$B$9)+E89*'Power Model'!$B$10/100,0) -> 6174 | O89: Unarmed +2; Melee +1 | Q89: Unarmed 3; Melee 2; Grit 3 | R89: Restricted stock; heavy power draw.
A90: Kestrel Defense Strike Servo | B90: trl_imp_x417 | C90: Arms | D90: 4 | E90: 113200 | F90: =ROUND(E90*0.8,0) -> 90560 | G90: 3 | H90: arms | I90: 65 | J90: ='Power Model'!$B$3*2^(D90-2) -> 4 | L90: =ROUND(E90*'Power Model'!$B$11,0) -> 28300 | M90: =ROUND(J90*'Power Model'!$B$4*('Power Model'!$B$7*'Power Model'!$B$8+'Power Model'!$B$9)+E90*'Power Model'!$B$10/100,0) -> 6399 | O90: Melee +3 | Q90: Melee 4; Grit 3 | R90: Restricted stock; heavy power draw.
A91: Volkov Armaments Haul Cabling | B91: trl_imp_x418 | C91: Arms | D91: 4 | E91: 117700 | F91: =ROUND(E91*0.8,0) -> 94160 | G91: 4 | H91: arms | I91: 68 | J91: ='Power Model'!$B$3*2^(D91-2) -> 4 | L91: =ROUND(E91*'Power Model'!$B$11,0) -> 29425 | M91: =ROUND(J91*'Power Model'!$B$4*('Power Model'!$B$7*'Power Model'!$B$8+'Power Model'!$B$9)+E91*'Power Model'!$B$10/100,0) -> 6624 | O91: Unarmed +2; Manual +1 | Q91: Unarmed 3; Manual 2; Grit 3 | R91: Restricted stock; heavy power draw.
A92: Blackmere Ordnance Smart Palm | B92: trl_imp_x419 | C92: Hands | D92: 4 | E92: 108700 | F92: =ROUND(E92*0.8,0) -> 86960 | G92: 3 | H92: arms | I92: 62 | J92: ='Power Model'!$B$3*2^(D92-2) -> 4 | L92: =ROUND(E92*'Power Model'!$B$11,0) -> 27175 | M92: =ROUND(J92*'Power Model'!$B$4*('Power Model'!$B$7*'Power Model'!$B$8+'Power Model'!$B$9)+E92*'Power Model'!$B$10/100,0) -> 6174 | O92: Ranged +3 | Q92: Ranged 4; Grit 3 | R92: Restricted stock; heavy power draw.
A93: Ironhold Systems Fine-Motor Set | B93: trl_imp_x420 | C93: Hands | D93: 4 | E93: 113200 | F93: =ROUND(E93*0.8,0) -> 90560 | G93: 4 | H93: arms | I93: 65 | J93: ='Power Model'!$B$3*2^(D93-2) -> 4 | L93: =ROUND(E93*'Power Model'!$B$11,0) -> 28300 | M93: =ROUND(J93*'Power Model'!$B$4*('Power Model'!$B$7*'Power Model'!$B$8+'Power Model'!$B$9)+E93*'Power Model'!$B$10/100,0) -> 6399 | O93: Engineering +2; Manual +1 | Q93: Engineering 3; Manual 2; Grit 3 | R93: Restricted stock; heavy power draw.
A94: Kestrel Defense Tool Fingers | B94: trl_imp_x421 | C94: Hands | D94: 4 | E94: 117700 | F94: =ROUND(E94*0.8,0) -> 94160 | G94: 3 | H94: arms | I94: 68 | J94: ='Power Model'!$B$3*2^(D94-2) -> 4 | L94: =ROUND(E94*'Power Model'!$B$11,0) -> 29425 | M94: =ROUND(J94*'Power Model'!$B$4*('Power Model'!$B$7*'Power Model'!$B$8+'Power Model'!$B$9)+E94*'Power Model'!$B$10/100,0) -> 6624 | O94: Artisan +3 | Q94: Artisan 4; Grit 3 | R94: Restricted stock; heavy power draw.
A95: Volkov Armaments Actuator | B95: trl_imp_x422 | C95: Legs | D95: 4 | E95: 108700 | F95: =ROUND(E95*0.8,0) -> 86960 | G95: 4 | H95: legs | I95: 62 | J95: ='Power Model'!$B$3*2^(D95-2) -> 4 | L95: =ROUND(E95*'Power Model'!$B$11,0) -> 27175 | M95: =ROUND(J95*'Power Model'!$B$4*('Power Model'!$B$7*'Power Model'!$B$8+'Power Model'!$B$9)+E95*'Power Model'!$B$10/100,0) -> 6174 | O95: Dodge +2; Grit +1 | Q95: Dodge 3; Grit 3 | R95: Restricted stock; heavy power draw.
A96: Blackmere Ordnance Shock Spring | B96: trl_imp_x423 | C96: Legs | D96: 4 | E96: 113200 | F96: =ROUND(E96*0.8,0) -> 90560 | G96: 3 | H96: legs | I96: 65 | J96: ='Power Model'!$B$3*2^(D96-2) -> 4 | L96: =ROUND(E96*'Power Model'!$B$11,0) -> 28300 | M96: =ROUND(J96*'Power Model'!$B$4*('Power Model'!$B$7*'Power Model'!$B$8+'Power Model'!$B$9)+E96*'Power Model'!$B$10/100,0) -> 6399 | O96: Streetwise +3 | Q96: Streetwise 4; Grit 3 | R96: Restricted stock; heavy power draw.
A97: Ironhold Systems Sprint Tendons | B97: trl_imp_x424 | C97: Legs | D97: 4 | E97: 117700 | F97: =ROUND(E97*0.8,0) -> 94160 | G97: 4 | H97: legs | I97: 68 | J97: ='Power Model'!$B$3*2^(D97-2) -> 4 | L97: =ROUND(E97*'Power Model'!$B$11,0) -> 29425 | M97: =ROUND(J97*'Power Model'!$B$4*('Power Model'!$B$7*'Power Model'!$B$8+'Power Model'!$B$9)+E97*'Power Model'!$B$10/100,0) -> 6624 | O97: Manual +2; Dodge +1 | Q97: Manual 3; Dodge 2; Grit 3 | R97: Restricted stock; heavy power draw.
A98: Helix Research Annex Trilobit | B98: trl_imp_x501 | C98: Head / cortex | D98: 5 | E98: 236900 | F98: =ROUND(E98*0.8,0) -> 189520 | G98: 4 | H98: head | I98: 104 | J98: ='Power Model'!$B$3*2^(D98-2) -> 8 | L98: =ROUND(E98*'Power Model'!$B$11,0) -> 59225 | M98: =ROUND(J98*'Power Model'!$B$4*('Power Model'!$B$7*'Power Model'!$B$8+'Power Model'!$B$9)+E98*'Power Model'!$B$10/100,0) -> 13323 | O98: Networking +3 | P98: 10 | Q98: Networking 4; Grit 4 | R98: Brain implant: holds 10 nanohack slots. Unproven research unit: may glitch when damaged, needs recalibration after each fight. Price and grade are beyond the current catalogue.
A99: Project NOCTURNE Trilobit | B99: trl_imp_x502 | C99: Head / cortex | D99: 5 | E99: 247000 | F99: =ROUND(E99*0.8,0) -> 197600 | G99: 4 | H99: head | I99: 106 | J99: ='Power Model'!$B$3*2^(D99-2) -> 8 | L99: =ROUND(E99*'Power Model'!$B$11,0) -> 61750 | M99: =ROUND(J99*'Power Model'!$B$4*('Power Model'!$B$7*'Power Model'!$B$8+'Power Model'!$B$9)+E99*'Power Model'!$B$10/100,0) -> 13828 | O99: Analysis +3 | P99: 10 | Q99: Analysis 4; Grit 4 | R99: Brain implant: holds 10 nanohack slots. Unproven research unit: may glitch when damaged, needs recalibration after each fight. Price and grade are beyond the current catalogue.
A100: Omen Labs Trilobit | B100: trl_imp_x503 | C100: Head / cortex | D100: 5 | E100: 257000 | F100: =ROUND(E100*0.8,0) -> 205600 | G100: 4 | H100: head | I100: 110 | J100: ='Power Model'!$B$3*2^(D100-2) -> 8 | L100: =ROUND(E100*'Power Model'!$B$11,0) -> 64250 | M100: =ROUND(J100*'Power Model'!$B$4*('Power Model'!$B$7*'Power Model'!$B$8+'Power Model'!$B$9)+E100*'Power Model'!$B$10/100,0) -> 14328 | O100: Implementation +3 | P100: 10 | Q100: Implementation 4; Grit 4 | R100: Brain implant: holds 10 nanohack slots. Unproven research unit: may glitch when damaged, needs recalibration after each fight. Price and grade are beyond the current catalogue.
...

Sheet Power Model
A1: Power and cost model (edit the yellow cells; the Example Implants tab recalculates)
A3: Latent draw of one Improved (grade 2) implant, kJ/h | B3: 1 | C3: Draft. Each grade doubles it: draw = this x 2^(grade-2).
A4: Hours in a week of full use | B4: 168
A5: Implants in a fully implanted person (one per layer) | B5: 8 | C5: Head, eyes, spine, chest, dermal, arms, hands, legs.
A6: Improved chest battery capacity, kJ | B6: =B3*B4*B5 -> 1344 | C6: =week x rig size x draw. an all-improved rig drains it in exactly one week. -> #VALUE!
A7: Power rate, yen per kJ | B7: 1 | C7: Same as the charging stations (POWER_RATE).
A8: District multiplier | B8: 1 | C8: 0.85 lower, 1.0 middle, 1.35 upper.
A9: Power tax, yen per kJ | B9: 0.1 | C9: Same as the charging stations (POWER_TAX).
A10: Implant tax, % of implant price per visit | B10: 5 | C10: Same as the charging stations (TAX_PCT).
A11: Repair cost at 100% damage, fraction of price | B11: 0.25 | C11: Quality fee scales linearly with damage.
A12: Reserve Cell capacity multiplier | B12: 3 | C12: Extra chest implants store this many times the standard battery of their grade.
A14: Check: hours an all-Improved rig runs on one Improved battery | B14: =B6/(B5*B3) -> 168 | C14: Should read 168.

Sheet Notes
A1: Tab 1 (Implants): the 12 implants in the game today. Edits here do not change the game.
A2: Tab 2 (Example Implants): invented designs, 24 per quality level plus one extra Prototype Trilobit. Not in the game.
A3: Quality levels by grade: 1 Basic, 2 Improved, 3 Quality, 4 Military, 5 Prototype (grade 5 is new).
A4: Durability doubles as health. Within a level, implants with smaller skill bonuses get more durability: dur = low + (high x 1.25 - low) x (1 - skill total / highest skill total in the level).
A5: Armor: every implant has at least 1; dermal implants are the armor-heavy layer. Armor applies to the limb group of the part (eyes: head, spine: chest, hands: arms).
A6: Layers: Chest and Dermal are separate. Dermal implants all lower Negotiation by 1.
A7: Nanohacks permitted (Trilobits only): Basic 2, Improved 4, Quality 6, Military 8, Prototype 10; the extra Prototype Trilobit holds 14 and has no skill bonus.
A8: Latent draw = Power Model!B3 x 2^(grade-2). An all-Improved rig of 8 implants (one per layer) drains one Improved chest battery in 168 hours.
A9: Battery: standard chest batteries store week x rig size x draw of their grade (they double per grade). Reserve Cells store 3x that and have no skill bonus.
A10: Prices are 10x the earlier example prices. Underground clinics charge 80%.
A11: Quality fee = the repair cost: 25% of price at 100% damage, scaling with damage.
A12: Recharge cost (one week) = draw x 168 h x (power rate x district + power tax) + implant tax on the price. It leaves out the old per-visit quality fee because that fee is now the repair cost.
... A14: Manufacturers and model names are invented.
